{
    "/js/app.js": "/js/app.js",
    "/js/app.f42a2bb607d85344c9b2.hot-update.js": "/js/app.f42a2bb607d85344c9b2.hot-update.js",
    "/js/app.86abbc0d80e74dba1045.hot-update.js": "/js/app.86abbc0d80e74dba1045.hot-update.js",
    "/js/app.e4c80f8d438bb2b88c58.hot-update.js": "/js/app.e4c80f8d438bb2b88c58.hot-update.js",
    "/js/app.dec47135b9caa0ebde67.hot-update.js": "/js/app.dec47135b9caa0ebde67.hot-update.js",
    "/js/app.b08dd10cf9c5fa9a612f.hot-update.js": "/js/app.b08dd10cf9c5fa9a612f.hot-update.js",
    "/js/app.a0c850558f4e0a1e3625.hot-update.js": "/js/app.a0c850558f4e0a1e3625.hot-update.js",
    "/js/app.ab62353f43bb3b5ec8d5.hot-update.js": "/js/app.ab62353f43bb3b5ec8d5.hot-update.js",
    "/js/app.fd4d6a83d7dbf1d9b9cd.hot-update.js": "/js/app.fd4d6a83d7dbf1d9b9cd.hot-update.js",
    "/js/app.b28db67d8d9c628037f6.hot-update.js": "/js/app.b28db67d8d9c628037f6.hot-update.js",
    "/js/app.0aea0176537b232922b6.hot-update.js": "/js/app.0aea0176537b232922b6.hot-update.js",
    "/js/app.44ecb5a9cdffa0b13a73.hot-update.js": "/js/app.44ecb5a9cdffa0b13a73.hot-update.js",
    "/js/app.8c45e2279663b1b0da49.hot-update.js": "/js/app.8c45e2279663b1b0da49.hot-update.js",
    "/js/app.f655899248abf584c616.hot-update.js": "/js/app.f655899248abf584c616.hot-update.js"
}
